browserstack_helper/AWS.py
browserstack_helper/__init__.py
browserstack_helper/android.py
browserstack_helper/ios.py
browserstack_helper/test_runner.py
byu_browserstack_helper-0.5.2.dist-info/LICENSE
byu_browserstack_helper-0.5.2.dist-info/METADATA
byu_browserstack_helper-0.5.2.dist-info/WHEEL
byu_browserstack_helper-0.5.2.dist-info/top_level.txt
byu_browserstack_helper-0.5.2.dist-info/RECORD
