Metadata-Version: 2.1
Name: byu-browserstack-helper
Version: 0.5.2
Summary: A package for helping with some of the QA teams most used functions
Home-page: https://github.com/byu-oit/browserstack-helper-library
Author: Mark Roth
Author-email: mark_roth@byu.edu
License: UNKNOWN
Platform: UNKNOWN
Classifier: Programming Language :: Python :: 3
Classifier: License :: OSI Approved :: Apache Software License 
Classifier: Operating System :: OS Independent
Requires-Python: >=3.8
Requires-Dist: boto3 (<1.17.0,>=1.16.0)
Requires-Dist: Appium-Python-Client (<1.1.0,>=1.0.0)
Requires-Dist: selenium (<4.0.0,>=3.0.0)
